skill_camera/LICENSE.md
skill_camera/README.md
skill_camera/__init__.py
skill_camera/skill.json
skill_camera/version.py
skill_camera/dialog/en-us/DefaultDuration.dialog
skill_camera/dialog/en-us/LaunchCamera.dialog
skill_camera/dialog/en-us/NoCamera.dialog
skill_camera/dialog/en-us/NothingToShow.dialog
skill_camera/dialog/en-us/PictureInsteadOfVideo.dialog
skill_camera/dialog/en-us/ServerNotSupported.dialog
skill_camera/dialog/en-us/ShowLatest.dialog
skill_camera/dialog/en-us/StartRecording.dialog
skill_camera/dialog/en-us/hour.list
skill_camera/dialog/en-us/minute.list
skill_camera/dialog/en-us/second.list
skill_camera/dialog/uk-ua/DefaultDuration.dialog
skill_camera/dialog/uk-ua/LaunchCamera.dialog
skill_camera/dialog/uk-ua/NoCamera.dialog
skill_camera/dialog/uk-ua/NothingToShow.dialog
skill_camera/dialog/uk-ua/PictureInsteadOfVideo.dialog
skill_camera/dialog/uk-ua/ServerNotSupported.dialog
skill_camera/dialog/uk-ua/ShowLatest.dialog
skill_camera/dialog/uk-ua/StartRecording.dialog
skill_camera/dialog/uk-ua/hour.list
skill_camera/dialog/uk-ua/minute.list
skill_camera/dialog/uk-ua/second.list
skill_camera/neon_skill_camera.egg-info/PKG-INFO
skill_camera/neon_skill_camera.egg-info/SOURCES.txt
skill_camera/neon_skill_camera.egg-info/dependency_links.txt
skill_camera/neon_skill_camera.egg-info/entry_points.txt
skill_camera/neon_skill_camera.egg-info/requires.txt
skill_camera/neon_skill_camera.egg-info/top_level.txt
skill_camera/ui/Camera.qml
skill_camera/ui/ControlBar.qml
skill_camera/ui/qmldir
skill_camera/ui/images/back.svg
skill_camera/ui/images/capture.svg
skill_camera/ui/images/close.svg
skill_camera/ui/sounds/clicking.wav
skill_camera/vocab/en-us/ShowLastIntent.intent
skill_camera/vocab/en-us/TakePicIntent.intent
skill_camera/vocab/en-us/TakeVidIntent.intent
skill_camera/vocab/en-us/duration.entity
skill_camera/vocab/uk-ua/ShowLastIntent.intent
skill_camera/vocab/uk-ua/TakePicIntent.intent
skill_camera/vocab/uk-ua/TakeVidIntent.intent
skill_camera/vocab/uk-ua/duration.entity
neon_skill_camera-1.2.0.dist-info/LICENSE.md
neon_skill_camera-1.2.0.dist-info/METADATA
neon_skill_camera-1.2.0.dist-info/WHEEL
neon_skill_camera-1.2.0.dist-info/entry_points.txt
neon_skill_camera-1.2.0.dist-info/top_level.txt
neon_skill_camera-1.2.0.dist-info/RECORD
